setup.py
pyqqclient/BarcodeExpiredException.py
pyqqclient/ContactDatabaseManager.py
pyqqclient/DatabaseManager.py
pyqqclient/FaultyLoginDataException.py
pyqqclient/GetBarcodeStepHandler.py
pyqqclient/GetPsessionidHandler.py
pyqqclient/GetPtwebqqHandler.py
pyqqclient/GetVfwebqqHandler.py
pyqqclient/GroupDatabaseManager.py
pyqqclient/Logger.py
pyqqclient/LoginExpiredException.py
pyqqclient/LoginFinalizeHandler.py
pyqqclient/LoginPipeline.py
pyqqclient/LoginSetupHandler.py
pyqqclient/LoginStepHandler.py
pyqqclient/MessageErrcodeException.py
pyqqclient/MessageHandler.py
pyqqclient/OnlineChecker.py
pyqqclient/PollingHandler.py
pyqqclient/SmartqqClient.py
pyqqclient/SmartqqHash.py
pyqqclient/SmartqqLoginPipeline.py
pyqqclient/SmartqqMessageHandler.py
pyqqclient/SynchronousPollingHandler.py
pyqqclient/UnknownUserException.py
pyqqclient/WaitForAuthHandler.py
python_smartqq_client.egg-info/PKG-INFO
python_smartqq_client.egg-info/SOURCES.txt
python_smartqq_client.egg-info/dependency_links.txt
python_smartqq_client.egg-info/requires.txt
python_smartqq_client.egg-info/top_level.txt